nioflux/__init__.py
nioflux/handler/__init__.py
nioflux/handler/error_notify.py
nioflux/handler/str_decode.py
nioflux/handler/str_encode.py
nioflux/pipeline/__init__.py
nioflux/pipeline/pipeline.py
nioflux/pipeline/stage.py
nioflux/server/__init__.py
nioflux/server/server.py
nioflux/util/__init__.py
nioflux/util/readsuntil.py
nioflux/util/transport_layer.py
nioflux-0.0.2.dist-info/licenses/LICENSE
nioflux-0.0.2.dist-info/METADATA
nioflux-0.0.2.dist-info/WHEEL
nioflux-0.0.2.dist-info/top_level.txt
nioflux-0.0.2.dist-info/RECORD
