Metadata-Version: 2.4
Name: nioflux
Version: 0.0.2
Summary: A lightweight asynchronous scalable TCP frame protocol server.
Requires-Python: >=3.10
License-File: LICENSE
Requires-Dist: vortezwohl>=0.0.10
Dynamic: license-file
